mixnmatchttp/__init__.py
mixnmatchttp/cache.py
mixnmatchttp/common.py
mixnmatchttp/endpoints.py
mixnmatchttp/servers.py
mixnmatchttp/handlers/__init__.py
mixnmatchttp/handlers/authenticator.py
mixnmatchttp/handlers/base.py
mixnmatchttp/handlers/cacher.py
mixnmatchttp/handlers/proxy.py
mixnmatchttp-0.2a0.post1.dist-info/LICENSE
mixnmatchttp-0.2a0.post1.dist-info/METADATA
mixnmatchttp-0.2a0.post1.dist-info/WHEEL
mixnmatchttp-0.2a0.post1.dist-info/top_level.txt
mixnmatchttp-0.2a0.post1.dist-info/RECORD
