Metadata-Version: 2.1
Name: mixnmatchttp
Version: 0.2a0.post1
Summary: Modular HTTP server: Auth, Caching, Proxy, and more
Home-page: https://github.com/aayla-secura/mixnmatchttp
Author: AaylaSecura1138
Author-email: aayla.secura.1138@gmail.com
License: UNKNOWN
Platform: UNKNOWN
Classifier: Programming Language :: Python :: 2
Classifier: Programming Language :: Python :: 2.7
Classifier: Programming Language :: Python :: 3
Classifier: Programming Language :: Python :: 3.4
Classifier: Programming Language :: Python :: 3.5
Classifier: Programming Language :: Python :: 3.6
Classifier: Programming Language :: Python :: 3.7
Classifier: License :: OSI Approved :: MIT License
Classifier: Operating System :: OS Independent
Requires-Dist: future (>=0.12)
Requires-Dist: wrapt (>=1)
